{"error":null,"success":true,"body":[{"displayName":"Spani ;3","score":5,"scoreParts":[{"type":"number","score":5,"name":"Boss Tier"},{"type":"time","score":34550,"name":"Game Time"},{"type":"time","score":353017000,"name":"Least Cash"}],"submissionTime":-1,"profile":"https://data.ninjakiwi.com/btd6/users/9cea458c8bc2abac1044da4c5d7be77fc50615b49d41d83d"},{"displayName":":3","score":5,"scoreParts":[{"type":"number","score":5,"name":"Boss Tier"},{"type":"time","score":34650,"name":"Game Time"},{"type":"time","score":295961000,"name":"Least Cash"}],"submissionTime":-1,"profile":"https://data.ninjakiwi.com/btd6/users/9fbf158ddb93afac1f4b8a1f5874e122c9574fb89c168e3f"},{"displayName":"Thee Player","score":5,"scoreParts":[{"type":"number","score":5,"name":"Boss Tier"},{"type":"time","score":34733,"name":"Game Time"},{"type":"time","score":36391000,"name":"Least Cash"}],"submissionTime":-1,"profile":"https://data.ninjakiwi.com/btd6/users/9fb815de8bc3f9f31810dc4d0b22e171cd024cb59f13de3f"},{"displayName":"BESTBATTLER8","score":5,"scoreParts":[{"type":"number","score":5,"name":"Boss Tier"},{"type":"time","score":34900,"name":"Game Time"},{"type":"time","score":125236000,"name":"Least Cash"}],"submissionTime":-1,"profile":"https://data.ninjakiwi.com/btd6/users/9fbe108a8c9fadf018148e4b0d20e5769e5215e99f11d83d"},{"displayName":"HalfYourPing","score":5,"scoreParts":[{"type":"number","score":5,"name":"Boss Tier"},{"type":"time","score":34917,"name":"Game Time"},{"type":"time","score":318742000,"name":"Least Cash"}],"submissionTime":-1,"profile":"https://data.ninjakiwi.com/btd6/users/9fbb44dd8994acad1b408e1a0975e122c5071ab5ca45de3e"},{"displayName":"Lawrence zhUwU","score":5,"scoreParts":[{"type":"number","score":5,"name":"Boss Tier"},{"type":"time","score":35033,"name":"Game Time"},{"type":"time","score":388137000,"name":"Least Cash"}],"submissionTime":-1,"profile":"https://data.ninjakiwi.com/btd6/users/9fbc44828cc4f9ac1a4a881f577bb276c90014b99d14df6e"},{"displayName":"RIGJUICE","score":5,"scoreParts":[{"type":"number","score":5,"name":"Boss Tier"},{"type":"time","score":35383,"name":"Game Time"},{"type":"time","score":257288000,"name":"Least Cash"}],"submissionTime":-1,"profile":"https://data.ninjakiwi.com/btd6/users/9cb74488da93aff11845dd1f5e74b470ca521ab99743da6c"},{"displayName":"ZooL","score":5,"scoreParts":[{"type":"number","score":5,"name":"Boss Tier"},{"type":"time","score":35450,"name":"Game Time"},{"type":"time","score":408174000,"name":"Least Cash"}],"submissionTime":-1,"profile":"https://data.ninjakiwi.com/btd6/users/9fbb4688dbc5aba249118a4f597ae170980748b49c45de3f"},{"displayName":"limitlesss","score":5,"scoreParts":[{"type":"number","score":5,"name":"Boss Tier"},{"type":"time","score":35517,"name":"Game Time"},{"type":"time","score":352725000,"name":"Least Cash"}],"submissionTime":-1,"profile":"https://data.ninjakiwi.com/btd6/users/9fbe15dade9eaff71c13891a0e72e2709e561ce89d13db31"},{"displayName":"Nstra0","score":5,"scoreParts":[{"type":"number","score":5,"name":"Boss Tier"},{"type":"time","score":35533,"name":"Game Time"},{"type":"time","score":369806000,"name":"Least Cash"}],"submissionTime":-1,"profile":"https://data.ninjakiwi.com/btd6/users/9fb944d8df9eabac4a44dc4b5970b326ca061bbfcf11dd3c"},{"displayName":"xrlylyl","score":5,"scoreParts":[{"type":"number","score":5,"name":"Boss Tier"},{"type":"time","score":35633,"name":"Game Time"},{"type":"time","score":250988000,"name":"Least Cash"}],"submissionTime":-1,"profile":"https://data.ninjakiwi.com/btd6/users/9fbe1edddcc7aaac1b40d91f5f26e576c40c48be9641d03e"},{"displayName":"Kirtap","score":5,"scoreParts":[{"type":"number","score":5,"name":"Boss Tier"},{"type":"time","score":35633,"name":"Game Time"},{"type":"time","score":306794000,"name":"Least Cash"}],"submissionTime":-1,"profile":"https://data.ninjakiwi.com/btd6/users/9ced11dfdb92fea41b4ad94e5675e474cd014fb4cc138a3b"},{"displayName":"Machine Monkey","score":5,"scoreParts":[{"type":"number","score":5,"name":"Boss Tier"},{"type":"time","score":35683,"name":"Game Time"},{"type":"time","score":120082000,"name":"Least Cash"}],"submissionTime":-1,"profile":"https://data.ninjakiwi.com/btd6/users/9fbb428ddfc4fef710468e1a5e7bee259d504cbcca14de39"},{"displayName":"CoolDudeBen999","score":5,"scoreParts":[{"type":"number","score":5,"name":"Boss Tier"},{"type":"time","score":35683,"name":"Game Time"},{"type":"time","score":150831000,"name":"Least Cash"}],"submissionTime":-1,"profile":"https://data.ninjakiwi.com/btd6/users/9cea15dadcc3fdf44c4186495827e571c8024cb89e19dc31"},{"displayName":"Natananos","score":5,"scoreParts":[{"type":"number","score":5,"name":"Boss Tier"},{"type":"time","score":35750,"name":"Game Time"},{"type":"time","score":23880000,"name":"Least Cash"}],"submissionTime":-1,"profile":"https://data.ninjakiwi.com/btd6/users/9fbe468c8c91fba44a46884b5c21e272c40614ee9c108b6e"},{"displayName":"RoMath101","score":5,"scoreParts":[{"type":"number","score":5,"name":"Boss Tier"},{"type":"time","score":35750,"name":"Game Time"},{"type":"time","score":267209000,"name":"Least Cash"}],"submissionTime":-1,"profile":"https://data.ninjakiwi.com/btd6/users/9fbb43d8d7c4fda71d418b495a27b0219e071cba9612df3c"},{"displayName":"FrogsRcool :)","score":5,"scoreParts":[{"type":"number","score":5,"name":"Boss Tier"},{"type":"time","score":35767,"name":"Game Time"},{"type":"time","score":401329000,"name":"Least Cash"}],"submissionTime":-1,"profile":"https://data.ninjakiwi.com/btd6/users/9fbb1e8cdb9efea34b108a480b21ee75c45748ef9716d16a"},{"displayName":"Druid :)","score":5,"scoreParts":[{"type":"number","score":5,"name":"Boss Tier"},{"type":"time","score":35817,"name":"Game Time"},{"type":"time","score":166411000,"name":"Least Cash"}],"submissionTime":-1,"profile":"https://data.ninjakiwi.com/btd6/users/9fb9108ed6c3fead4b41de4d5977e576c90415bfcb17dd39"},{"displayName":"Heavenbound22","score":5,"scoreParts":[{"type":"number","score":5,"name":"Boss Tier"},{"type":"time","score":35817,"name":"Game Time"},{"type":"time","score":200697000,"name":"Least Cash"}],"submissionTime":-1,"profile":"https://data.ninjakiwi.com/btd6/users/9cea118b8997acac1b17db420c71e0729e0319bbcf19db3b"},{"displayName":"Osc3ar","score":5,"scoreParts":[{"type":"number","score":5,"name":"Boss Tier"},{"type":"time","score":35817,"name":"Game Time"},{"type":"time","score":310161000,"name":"Least Cash"}],"submissionTime":-1,"profile":"https://data.ninjakiwi.com/btd6/users/9cea1ed9dc96faa31e4086435f75e7709f0214bb98458a3d"},{"displayName":"FraiseTagada","score":5,"scoreParts":[{"type":"number","score":5,"name":"Boss Tier"},{"type":"time","score":35867,"name":"Game Time"},{"type":"time","score":92018000,"name":"Least Cash"}],"submissionTime":-1,"profile":"https://data.ninjakiwi.com/btd6/users/9ce9418cdac2a8a14e458a4e5871e77f98511feaca118a3e"},{"displayName":"BTD Express","score":5,"scoreParts":[{"type":"number","score":5,"name":"Boss Tier"},{"type":"time","score":35883,"name":"Game Time"},{"type":"time","score":386087000,"name":"Least Cash"}],"submissionTime":-1,"profile":"https://data.ninjakiwi.com/btd6/users/9ceb1e83d695fda51f4a8f1f5874e17e9d0218e89e18896e"},{"displayName":"Tofudeamendoa","score":5,"scoreParts":[{"type":"number","score":5,"name":"Boss Tier"},{"type":"time","score":35933,"name":"Game Time"},{"type":"time","score":232900000,"name":"Least Cash"}],"submissionTime":-1,"profile":"https://data.ninjakiwi.com/btd6/users/9fbf15828b97fcf1491187425c25e771ca504fb5cc17df3d"},{"displayName":"Player3964978","score":5,"scoreParts":[{"type":"number","score":5,"name":"Boss Tier"},{"type":"time","score":35950,"name":"Game Time"},{"type":"time","score":370999000,"name":"Least Cash"}],"submissionTime":-1,"profile":"https://data.ninjakiwi.com/btd6/users/9fbb1f8ad890aaf11a408d1d0b7be625c40d18e8cd418a3c"},{"displayName":"Cloud","score":5,"scoreParts":[{"type":"number","score":5,"name":"Boss Tier"},{"type":"time","score":35950,"name":"Game Time"},{"type":"time","score":409976000,"name":"Least Cash"}],"submissionTime":-1,"profile":"https://data.ninjakiwi.com/btd6/users/9fbf118bdc93a8ac1045881e5977e323985648e997178d6d"}],"model":{"name":"_btd6bossleaderboard","parameters":{"displayName":{"description":"The display name for this user","type":"string"},"score":{"description":"The Boss score in milliseconds (lower is better)","type":"number"},"scoreParts":{"description":"When the leaderboard includes multiple scores they will be included here","type":"array"},"submissionTime":{"description":"The epoch time in milliseconds","type":"number"},"profile":{"description":"URL to the players public profile","type":"string"}}},"next":"https://data.ninjakiwi.com/btd6/bosses/Bloonarius59_map5b0gq/leaderboard/standard/1?page=2","prev":null}