{"error":null,"success":true,"body":[{"displayName":"Gone","score":5,"scoreParts":[{"type":"number","score":5,"name":"Boss Tier"},{"type":"time","score":64983,"name":"Least Cash"},{"type":"time","score":395259000,"name":"Game Time"}],"submissionTime":-1,"profile":"https://data.ninjakiwi.com/btd6/users/9fbe1fddddc4fef64d41861f5873e377c9524eb99614d86c"},{"displayName":"Storyteller","score":5,"scoreParts":[{"type":"number","score":5,"name":"Boss Tier"},{"type":"time","score":65350,"name":"Least Cash"},{"type":"time","score":346444000,"name":"Game Time"}],"submissionTime":-1,"profile":"https://data.ninjakiwi.com/btd6/users/9fbd14ded696aba54c478a1e0b72e223980115bc99148d31"},{"displayName":"Olinequ","score":5,"scoreParts":[{"type":"number","score":5,"name":"Boss Tier"},{"type":"time","score":65400,"name":"Least Cash"},{"type":"time","score":403873000,"name":"Game Time"}],"submissionTime":-1,"profile":"https://data.ninjakiwi.com/btd6/users/9fb710d9d9c5fba41c468b4d0921ef249a0c4bbacf418e6c"},{"displayName":"Carl","score":5,"scoreParts":[{"type":"number","score":5,"name":"Boss Tier"},{"type":"time","score":65533,"name":"Least Cash"},{"type":"time","score":411841000,"name":"Game Time"}],"submissionTime":-1,"profile":"https://data.ninjakiwi.com/btd6/users/9ceb13df8dc4fca31a46864c5926e7259a5648e9c845df3b"},{"displayName":"Player","score":5,"scoreParts":[{"type":"number","score":5,"name":"Boss Tier"},{"type":"time","score":66100,"name":"Least Cash"},{"type":"time","score":268671000,"name":"Game Time"}],"submissionTime":-1,"profile":"https://data.ninjakiwi.com/btd6/users/9fb815de8bc3f9f31810dc4d0b22e171cd024cb59f13de3f"},{"displayName":"Ghgys","score":5,"scoreParts":[{"type":"number","score":5,"name":"Boss Tier"},{"type":"time","score":66267,"name":"Least Cash"},{"type":"time","score":418460000,"name":"Game Time"}],"submissionTime":-1,"profile":"https://data.ninjakiwi.com/btd6/users/9ced138ed893f8a01f428e1a5a77ef21cd074eedca148b6b"},{"displayName":"ikun","score":5,"scoreParts":[{"type":"number","score":5,"name":"Boss Tier"},{"type":"time","score":66317,"name":"Least Cash"},{"type":"time","score":124629000,"name":"Game Time"}],"submissionTime":-1,"profile":"https://data.ninjakiwi.com/btd6/users/9fbd4382d996fef34a4bdd4c0d7ab3719d064ce89845893d"},{"displayName":"Mostafa","score":5,"scoreParts":[{"type":"number","score":5,"name":"Boss Tier"},{"type":"time","score":72633,"name":"Least Cash"},{"type":"time","score":426547000,"name":"Game Time"}],"submissionTime":-1,"profile":"https://data.ninjakiwi.com/btd6/users/9fb91e838bc5f8a610138f1f5e74ef759a0118e9cc428d6c"},{"displayName":"Express","score":5,"scoreParts":[{"type":"number","score":5,"name":"Boss Tier"},{"type":"time","score":73383,"name":"Least Cash"},{"type":"time","score":263522000,"name":"Game Time"}],"submissionTime":-1,"profile":"https://data.ninjakiwi.com/btd6/users/9fb8138dd8c0fdad19408b435c22e47e9a0c1aee9e13de6d"},{"displayName":"Mabopolis :D","score":5,"scoreParts":[{"type":"number","score":5,"name":"Boss Tier"},{"type":"time","score":73467,"name":"Least Cash"},{"type":"time","score":220080000,"name":"Game Time"}],"submissionTime":-1,"profile":"https://data.ninjakiwi.com/btd6/users/9fba10d8d79ffea31847da435774e722990118ba9c438b31"},{"displayName":"Phatbeet2002","score":5,"scoreParts":[{"type":"number","score":5,"name":"Boss Tier"},{"type":"time","score":75817,"name":"Least Cash"},{"type":"time","score":387795000,"name":"Game Time"}],"submissionTime":-1,"profile":"https://data.ninjakiwi.com/btd6/users/9fb6178889c0aaa34d108f4a0d70e322cd051eef96118c3f"},{"displayName":"Shrimploon","score":5,"scoreParts":[{"type":"number","score":5,"name":"Boss Tier"},{"type":"time","score":76450,"name":"Least Cash"},{"type":"time","score":404875000,"name":"Game Time"}],"submissionTime":-1,"profile":"https://data.ninjakiwi.com/btd6/users/9fb91f89d793afa41f44dc485870e6729f041db9ca12dc3a"},{"displayName":"Friends Collec","score":5,"scoreParts":[{"type":"number","score":5,"name":"Boss Tier"},{"type":"time","score":77516,"name":"Least Cash"},{"type":"time","score":415232000,"name":"Game Time"}],"submissionTime":-1,"profile":"https://data.ninjakiwi.com/btd6/users/9cb8168389c0aaf018418c4d0e7be572c80719e89b11da3b"},{"displayName":"Monster","score":5,"scoreParts":[{"type":"number","score":5,"name":"Boss Tier"},{"type":"time","score":78084,"name":"Least Cash"},{"type":"time","score":220834000,"name":"Game Time"}],"submissionTime":-1,"profile":"https://data.ninjakiwi.com/btd6/users/9cb6178ddcc7f9f01a4a874c5d25e726cc5548be97468b6a"},{"displayName":"FraiseTagada","score":5,"scoreParts":[{"type":"number","score":5,"name":"Boss Tier"},{"type":"time","score":78250,"name":"Least Cash"},{"type":"time","score":207046000,"name":"Game Time"}],"submissionTime":-1,"profile":"https://data.ninjakiwi.com/btd6/users/9ce9418cdac2a8a14e458a4e5871e77f98511feaca118a3e"},{"displayName":"ZooL","score":5,"scoreParts":[{"type":"number","score":5,"name":"Boss Tier"},{"type":"time","score":79350,"name":"Least Cash"},{"type":"time","score":343495000,"name":"Game Time"}],"submissionTime":-1,"profile":"https://data.ninjakiwi.com/btd6/users/9fbb4688dbc5aba249118a4f597ae170980748b49c45de3f"},{"displayName":"Kerone","score":5,"scoreParts":[{"type":"number","score":5,"name":"Boss Tier"},{"type":"time","score":79717,"name":"Least Cash"},{"type":"time","score":68381000,"name":"Game Time"}],"submissionTime":-1,"profile":"https://data.ninjakiwi.com/btd6/users/9cea168adb95aba14b458b420b25e77fce551dbbcf158a31"},{"displayName":"philia093","score":5,"scoreParts":[{"type":"number","score":5,"name":"Boss Tier"},{"type":"time","score":80783,"name":"Least Cash"},{"type":"time","score":107485000,"name":"Game Time"}],"submissionTime":-1,"profile":"https://data.ninjakiwi.com/btd6/users/9fba13d98d95aca24e4a884b5e71e67fce034fefca45db38"},{"displayName":"PotatoBucco271","score":5,"scoreParts":[{"type":"number","score":5,"name":"Boss Tier"},{"type":"time","score":81383,"name":"Least Cash"},{"type":"time","score":46783000,"name":"Game Time"}],"submissionTime":-1,"profile":"https://data.ninjakiwi.com/btd6/users/9fb712828bc0fda31d45db185b76e07ec95715b4ca18896e"},{"displayName":"GG BOND","score":5,"scoreParts":[{"type":"number","score":5,"name":"Boss Tier"},{"type":"time","score":82500,"name":"Least Cash"},{"type":"time","score":100293000,"name":"Game Time"}],"submissionTime":-1,"profile":"https://data.ninjakiwi.com/btd6/users/9fbc1edf8c94abf71c42da1a5c20b7719e074cb5c819896a"},{"displayName":"TealZebra3485","score":5,"scoreParts":[{"type":"number","score":5,"name":"Boss Tier"},{"type":"time","score":82817,"name":"Least Cash"},{"type":"time","score":402627000,"name":"Game Time"}],"submissionTime":-1,"profile":"https://data.ninjakiwi.com/btd6/users/9fb91f898dc2f9f71a10d9425973b47ec80c19eacc44dc3a"},{"displayName":"pickandshot","score":5,"scoreParts":[{"type":"number","score":5,"name":"Boss Tier"},{"type":"time","score":86300,"name":"Least Cash"},{"type":"time","score":23712000,"name":"Game Time"}],"submissionTime":-1,"profile":"https://data.ninjakiwi.com/btd6/users/9cea10df8d95f1ac1c43dd485a26e77fce554fb99d13dc6a"},{"displayName":"Rubikscuber","score":5,"scoreParts":[{"type":"number","score":5,"name":"Boss Tier"},{"type":"time","score":86483,"name":"Least Cash"},{"type":"time","score":90774000,"name":"Game Time"}],"submissionTime":-1,"profile":"https://data.ninjakiwi.com/btd6/users/9fbc1ed889c2f9f04d118d490e77e323c5551ae89c19d83e"},{"displayName":"Jade4242","score":5,"scoreParts":[{"type":"number","score":5,"name":"Boss Tier"},{"type":"time","score":86983,"name":"Least Cash"},{"type":"time","score":309888000,"name":"Game Time"}],"submissionTime":-1,"profile":"https://data.ninjakiwi.com/btd6/users/9fbc46d8da97adf71d1388195d76b573c90648bd9a178b39"},{"displayName":"bloodworker9","score":5,"scoreParts":[{"type":"number","score":5,"name":"Boss Tier"},{"type":"time","score":87350,"name":"Least Cash"},{"type":"time","score":411246000,"name":"Game Time"}],"submissionTime":-1,"profile":"https://data.ninjakiwi.com/btd6/users/9fbf10dfd796a8a51d4b8a430925e775cd564bbe97148e31"}],"model":{"name":"_btd6bossleaderboard","parameters":{"displayName":{"description":"The display name for this user","type":"string"},"score":{"description":"The Boss score in milliseconds (lower is better)","type":"number"},"scoreParts":{"description":"When the leaderboard includes multiple scores they will be included here","type":"array"},"submissionTime":{"description":"The epoch time in milliseconds","type":"number"},"profile":{"description":"URL to the players public profile","type":"string"}}},"next":"https://data.ninjakiwi.com/btd6/bosses/Phayze27_mltto1x2/leaderboard/standard/1?page=2","prev":null,"maxPages":40}