{"error":null,"success":true,"body":[{"displayName":"WhyTho","score":5,"scoreParts":[{"type":"number","score":5,"name":"Boss Tier"},{"type":"number","score":54,"name":"Tier Count"},{"type":"time","score":1989600,"name":"Game Time"},{"type":"time","score":412266000,"name":"Submission Time"}],"submissionTime":-1,"profile":"https://data.ninjakiwi.com/btd6/users/9fb91f898c93f9f04d11da4a5f26e124cc021ded9f11d86b"},{"displayName":"lush life","score":5,"scoreParts":[{"type":"number","score":5,"name":"Boss Tier"},{"type":"number","score":55,"name":"Tier Count"},{"type":"time","score":1865000,"name":"Game Time"},{"type":"time","score":355668000,"name":"Submission Time"}],"submissionTime":-1,"profile":"https://data.ninjakiwi.com/btd6/users/9fbf43d9d796aaac1c41de4e5e7be672cc511aeacc138a39"},{"displayName":"VadimX","score":5,"scoreParts":[{"type":"number","score":5,"name":"Boss Tier"},{"type":"number","score":56,"name":"Tier Count"},{"type":"time","score":1909600,"name":"Game Time"},{"type":"time","score":337866000,"name":"Submission Time"}],"submissionTime":-1,"profile":"https://data.ninjakiwi.com/btd6/users/9ce9418b89c2f9f41a428c1a5a70e77f9d031beeca46d96a"},{"displayName":"Dawid","score":5,"scoreParts":[{"type":"number","score":5,"name":"Boss Tier"},{"type":"number","score":56,"name":"Tier Count"},{"type":"time","score":1923400,"name":"Game Time"},{"type":"time","score":403848000,"name":"Submission Time"}],"submissionTime":-1,"profile":"https://data.ninjakiwi.com/btd6/users/9fbc44d8dd97fbf64c11871e0e27e7249d5215bb9914de31"},{"displayName":"Potato","score":5,"scoreParts":[{"type":"number","score":5,"name":"Boss Tier"},{"type":"number","score":56,"name":"Tier Count"},{"type":"time","score":1926700,"name":"Game Time"},{"type":"time","score":338706000,"name":"Submission Time"}],"submissionTime":-1,"profile":"https://data.ninjakiwi.com/btd6/users/9fbb4688dbc5aba249118a4f597ae170980748b49c45de3f"},{"displayName":"Arne","score":5,"scoreParts":[{"type":"number","score":5,"name":"Boss Tier"},{"type":"number","score":56,"name":"Tier Count"},{"type":"time","score":2003700,"name":"Game Time"},{"type":"time","score":286818000,"name":"Submission Time"}],"submissionTime":-1,"profile":"https://data.ninjakiwi.com/btd6/users/9fbe11de8cc2fea04b4488425e77e576c5011cbf9842d93f"},{"displayName":"YOYOCHAIN","score":5,"scoreParts":[{"type":"number","score":5,"name":"Boss Tier"},{"type":"number","score":56,"name":"Tier Count"},{"type":"time","score":2071200,"name":"Game Time"},{"type":"time","score":399582000,"name":"Submission Time"}],"submissionTime":-1,"profile":"https://data.ninjakiwi.com/btd6/users/9fb713dd8b94fda61e118b4b0a76e673cb554cbc9914db6b"},{"displayName":"Doruat","score":5,"scoreParts":[{"type":"number","score":5,"name":"Boss Tier"},{"type":"number","score":56,"name":"Tier Count"},{"type":"time","score":2168000,"name":"Game Time"},{"type":"time","score":144432000,"name":"Submission Time"}],"submissionTime":-1,"profile":"https://data.ninjakiwi.com/btd6/users/9fba14dedd96faa44b43da4d0976b776c80518e99619893e"},{"displayName":"OnlyFarms","score":5,"scoreParts":[{"type":"number","score":5,"name":"Boss Tier"},{"type":"number","score":56,"name":"Tier Count"},{"type":"time","score":2185900,"name":"Game Time"},{"type":"time","score":181782000,"name":"Submission Time"}],"submissionTime":-1,"profile":"https://data.ninjakiwi.com/btd6/users/9fbf15da8d9ffdad1814dd4f5f7ae373cc064cb9c8118e3f"},{"displayName":"SauceMan","score":5,"scoreParts":[{"type":"number","score":5,"name":"Boss Tier"},{"type":"number","score":56,"name":"Tier Count"},{"type":"time","score":2209700,"name":"Game Time"},{"type":"time","score":313230000,"name":"Submission Time"}],"submissionTime":-1,"profile":"https://data.ninjakiwi.com/btd6/users/9ceb1f8fd895afa61943dc4c0b26e77fc9551bbbcf42d938"},{"displayName":"lapidusss","score":5,"scoreParts":[{"type":"number","score":5,"name":"Boss Tier"},{"type":"number","score":59,"name":"Tier Count"},{"type":"time","score":2088000,"name":"Game Time"},{"type":"time","score":292950000,"name":"Submission Time"}],"submissionTime":-1,"profile":"https://data.ninjakiwi.com/btd6/users/9fba1783dbc2fda44c13de1a0e7be024ce574cefcf44dc3c"},{"displayName":"CLens","score":5,"scoreParts":[{"type":"number","score":5,"name":"Boss Tier"},{"type":"number","score":59,"name":"Tier Count"},{"type":"time","score":2180200,"name":"Game Time"},{"type":"time","score":276942000,"name":"Submission Time"}],"submissionTime":-1,"profile":"https://data.ninjakiwi.com/btd6/users/9fb6178cd893aaac18438c1d0a25b4749a0718b4cc188a69"},{"displayName":"AndreyBTW","score":5,"scoreParts":[{"type":"number","score":5,"name":"Boss Tier"},{"type":"number","score":59,"name":"Tier Count"},{"type":"time","score":2289400,"name":"Game Time"},{"type":"time","score":241182000,"name":"Submission Time"}],"submissionTime":-1,"profile":"https://data.ninjakiwi.com/btd6/users/9fbf468dd8c2a8f31e40da1d0c7ae67fc90514bacf448a3c"},{"displayName":"YazanKeswany","score":5,"scoreParts":[{"type":"number","score":5,"name":"Boss Tier"},{"type":"number","score":60,"name":"Tier Count"},{"type":"time","score":1806300,"name":"Game Time"},{"type":"time","score":330810000,"name":"Submission Time"}],"submissionTime":-1,"profile":"https://data.ninjakiwi.com/btd6/users/9fbc4682da97a8a34d11db4b5977e175cb0714b49617d03f"},{"displayName":"TopElite1162","score":5,"scoreParts":[{"type":"number","score":5,"name":"Boss Tier"},{"type":"number","score":60,"name":"Tier Count"},{"type":"time","score":2047500,"name":"Game Time"},{"type":"time","score":215106000,"name":"Submission Time"}],"submissionTime":-1,"profile":"https://data.ninjakiwi.com/btd6/users/9fb91edfd994ffa31e438f4d0d73e470c9021cee9a45d03f"},{"displayName":"Salmonella","score":5,"scoreParts":[{"type":"number","score":5,"name":"Boss Tier"},{"type":"number","score":60,"name":"Tier Count"},{"type":"time","score":2123600,"name":"Game Time"},{"type":"time","score":89778000,"name":"Submission Time"}],"submissionTime":-1,"profile":"https://data.ninjakiwi.com/btd6/users/9cee1f8ddcc7f9a21f47864f5722ee22cc5714ea9d17d93a"},{"displayName":"IndieJ86","score":5,"scoreParts":[{"type":"number","score":5,"name":"Boss Tier"},{"type":"number","score":60,"name":"Tier Count"},{"type":"time","score":2168300,"name":"Game Time"},{"type":"time","score":219192000,"name":"Submission Time"}],"submissionTime":-1,"profile":"https://data.ninjakiwi.com/btd6/users/9fbe178d8c9efaa51b458f4f0e27e474c8514ceeca17da3b"},{"displayName":"Tendo Kei","score":5,"scoreParts":[{"type":"number","score":5,"name":"Boss Tier"},{"type":"number","score":60,"name":"Tier Count"},{"type":"time","score":2285700,"name":"Game Time"},{"type":"time","score":119760000,"name":"Submission Time"}],"submissionTime":-1,"profile":"https://data.ninjakiwi.com/btd6/users/9fbf42898b90afa44b468b4f5621e523cc001db99d42dc31"},{"displayName":"Lynx<3Sauda","score":5,"scoreParts":[{"type":"number","score":5,"name":"Boss Tier"},{"type":"number","score":61,"name":"Tier Count"},{"type":"time","score":2004400,"name":"Game Time"},{"type":"time","score":57222000,"name":"Submission Time"}],"submissionTime":-1,"profile":"https://data.ninjakiwi.com/btd6/users/9fbb43dd8bc7f8a6494286420e21ef24cb0049bf9b428d6d"},{"displayName":"Express","score":5,"scoreParts":[{"type":"number","score":5,"name":"Boss Tier"},{"type":"number","score":61,"name":"Tier Count"},{"type":"time","score":2041600,"name":"Game Time"},{"type":"time","score":94926000,"name":"Submission Time"}],"submissionTime":-1,"profile":"https://data.ninjakiwi.com/btd6/users/9fb8138dd8c0fdad19408b435c22e47e9a0c1aee9e13de6d"},{"displayName":"shxrt","score":5,"scoreParts":[{"type":"number","score":5,"name":"Boss Tier"},{"type":"number","score":61,"name":"Tier Count"},{"type":"time","score":2063200,"name":"Game Time"},{"type":"time","score":162282000,"name":"Submission Time"}],"submissionTime":-1,"profile":"https://data.ninjakiwi.com/btd6/users/9fbf15de8bc3ada4181186185971e771cb504cb89844df30"},{"displayName":"Tristan","score":5,"scoreParts":[{"type":"number","score":5,"name":"Boss Tier"},{"type":"number","score":61,"name":"Tier Count"},{"type":"time","score":2066800,"name":"Game Time"},{"type":"time","score":66240000,"name":"Submission Time"}],"submissionTime":-1,"profile":"https://data.ninjakiwi.com/btd6/users/9fb71e8ddd96f0f34e11884f5822e426990219b897458d3e"},{"displayName":"OliveKnight897","score":5,"scoreParts":[{"type":"number","score":5,"name":"Boss Tier"},{"type":"number","score":61,"name":"Tier Count"},{"type":"time","score":2069900,"name":"Game Time"},{"type":"time","score":338814000,"name":"Submission Time"}],"submissionTime":-1,"profile":"https://data.ninjakiwi.com/btd6/users/9fb842d9db9fa8ad4c10d91e0971e271ce054cba9f438c30"},{"displayName":"Pavel_Bure","score":5,"scoreParts":[{"type":"number","score":5,"name":"Boss Tier"},{"type":"number","score":61,"name":"Tier Count"},{"type":"time","score":2093200,"name":"Game Time"},{"type":"time","score":253242000,"name":"Submission Time"}],"submissionTime":-1,"profile":"https://data.ninjakiwi.com/btd6/users/9fbc138fdec3f1a51044d9425726b47ecb501eb89f12d931"},{"displayName":"Dohhaaja","score":5,"scoreParts":[{"type":"number","score":5,"name":"Boss Tier"},{"type":"number","score":61,"name":"Tier Count"},{"type":"time","score":2114400,"name":"Game Time"},{"type":"time","score":123792000,"name":"Submission Time"}],"submissionTime":-1,"profile":"https://data.ninjakiwi.com/btd6/users/9cbb1f8adac0f8a7494387190c74e076c95014edcd15d16b"}],"model":{"name":"_btd6bossleaderboard","parameters":{"displayName":{"description":"The display name for this user","type":"string"},"score":{"description":"The Boss score in milliseconds (lower is better)","type":"number"},"scoreParts":{"description":"When the leaderboard includes multiple scores they will be included here","type":"array"},"submissionTime":{"description":"The epoch time in milliseconds","type":"number"},"profile":{"description":"URL to the players public profile","type":"string"}}},"next":"https://data.ninjakiwi.com/btd6/bosses/Blastapopoulos15New2_mkhon93q/leaderboard/standard/1?page=2","prev":null,"maxPages":40}